<fieldingoption>
    <player id="Fielder_0">
        <startpos x="1.072340" y="-2.909091" />
        <sequence name="Basic04b.anm" />
    </player>
    <player id="Fielder_1">
        <startpos x="-2.621276" y="-1.212121" />
        <sequence name="Basic04b.anm" />
    </player>
    <player id="Fielder_2">
        <startpos x="2.680851" y="-1.454545" />
        <sequence name="Basic04b.anm" />
    </player>
    <player id="Fielder_3">
        <startpos x="4.170213" y="0.909091" />
        <sequence name="Basic04b.anm" />
    </player>
    <player id="Fielder_4">
        <startpos x="-6.195745" y="3.090909" />
        <sequence name="Basic04b.anm" />
    </player>
    <player id="Fielder_5">
        <startpos x="1.029999" y="1.584999" />
        <sequence name="Slip01.anm" />
    </player>
    <player id="Fielder_6">
        <startpos x="-0.953191" y="-2.909091" />
        <sequence name="Basic04b.anm" />
    </player>
    <player id="Fielder_7">
        <startpos x="0.500000" y="1.859999" />
        <sequence name="Slip01.anm" />
    </player>
    <player id="Fielder_8">
        <startpos x="-2.621276" y="0.787879" />
        <sequence name="Basic04b.anm" />
    </player>
</fieldingoption>
