<fieldingoption>
    <player id="Fielder_0">
        <startpos x="2.209999" y="0.325000" />
        <sequence name="Basic04b.anm" />
    </player>
    <player id="Fielder_6">
        <startpos x="6.919962" y="-0.490000" />
        <sequence name="Basic04b.anm" />
    </player>
    <player id="Fielder_2">
        <startpos x="1.664941" y="-2.354991" />
        <sequence name="Basic04b.anm" />
    </player>
    <player id="Fielder_3">
        <startpos x="1.754995" y="-6.899964" />
        <sequence name="Basic04b.anm" />
    </player>
    <player id="Fielder_4">
        <startpos x="-2.429995" y="-6.709939" />
        <sequence name="Basic04b.anm" />
    </player>
    <player id="Fielder_5">
        <startpos x="-5.764973" y="-3.859951" />
        <sequence name="Basic04b.anm" />
    </player>
    <player id="Fielder_1">
        <startpos x="-2.229999" y="0.010000" />
        <sequence name="Basic04b.anm" />
    </player>
    <player id="Fielder_7">
        <startpos x="-6.774949" y="1.419979" />
        <sequence name="Basic04b.anm" />
    </player>
    <player id="Fielder_8">
        <startpos x="-1.725000" y="2.165028" />
        <sequence name="Basic04b.anm" />
    </player>
</fieldingoption>
