<fieldingoption>
    <player id="Fielder_0">
        <startpos x="2.253731" y="1.902985" />
        <sequence name="Basic04b.anm" />
    </player>
    <player id="Fielder_1">
        <startpos x="0.280000" y="1.989999" />
        <sequence name="Slip01.anm" />
    </player>
    <player id="Fielder_2">
        <startpos x="1.365672" y="-2.233831" />
        <sequence name="Basic04b.anm" />
    </player>
    <player id="Fielder_3">
        <startpos x="-1.365672" y="-2.196517" />
        <sequence name="Basic04b.anm" />
    </player>
    <player id="Fielder_4">
        <startpos x="-2.639303" y="-1.019900" />
        <sequence name="Basic04b.anm" />
    </player>
    <player id="Fielder_5">
        <startpos x="-2.703980" y="1.273632" />
        <sequence name="Basic04b.anm" />
    </player>
    <player id="Fielder_6">
        <startpos x="-6.059970" y="3.699988" />
        <sequence name="Basic04b.anm" />
    </player>
    <player id="Fielder_7">
        <startpos x="2.686567" y="-0.960199" />
        <sequence name="Basic04b.anm" />
    </player>
    <player id="Fielder_8">
        <startpos x="6.499975" y="-2.799997" />
        <sequence name="Basic04b.anm" />
    </player>
</fieldingoption>
